<?xml version="1.0" ?>
<services>
	<service id="Service-8">
		<parameter id="I-20"/>
		<parameter id="I-21"/>
		<parameter id="O-23"/>
		<parameter id="O-24"/>
		<parameter id="O-25"/>
		<parameter id="O-26"/>
	</service>
	<service id="Service-9">
		<parameter id="I-22"/>
		<parameter id="I-21"/>
		<parameter id="I-19"/>
		<parameter id="O-27"/>
		<parameter id="O-28"/>
	</service>
	<service id="Service-19">
		<parameter id="I-49"/>
		<parameter id="I-50"/>
		<parameter id="O-58"/>
		<parameter id="O-59"/>
		<parameter id="O-60"/>
		<parameter id="O-61"/>
	</service>
	<service id="Service-20">
		<parameter id="I-52"/>
		<parameter id="I-49"/>
		<parameter id="I-50"/>
		<parameter id="I-55"/>
		<parameter id="I-54"/>
		<parameter id="O-62"/>
		<parameter id="O-63"/>
		<parameter id="O-64"/>
		<parameter id="O-65"/>
	</service>
	<service id="Service-30">
		<parameter id="I-79"/>
		<parameter id="I-77"/>
		<parameter id="I-76"/>
		<parameter id="O-84"/>
		<parameter id="O-85"/>
		<parameter id="O-86"/>
		<parameter id="O-87"/>
	</service>
	<service id="Service-33">
		<parameter id="I-85"/>
		<parameter id="I-82"/>
		<parameter id="O-95"/>
		<parameter id="O-96"/>
		<parameter id="O-97"/>
	</service>
	<service id="Service-34">
		<parameter id="I-88"/>
		<parameter id="I-93"/>
		<parameter id="I-92"/>
		<parameter id="I-91"/>
		<parameter id="O-98"/>
		<parameter id="O-99"/>
		<parameter id="O-100"/>
	</service>
	<service id="Service-35">
		<parameter id="I-88"/>
		<parameter id="O-101"/>
	</service>
	<service id="Service-36">
		<parameter id="I-88"/>
		<parameter id="I-89"/>
		<parameter id="O-102"/>
	</service>
	<service id="Service-43">
		<parameter id="I-111"/>
		<parameter id="O-119"/>
		<parameter id="O-120"/>
		<parameter id="O-121"/>
		<parameter id="O-122"/>
	</service>
	<service id="Service-48">
		<parameter id="I-126"/>
		<parameter id="I-127"/>
		<parameter id="I-124"/>
		<parameter id="I-123"/>
		<parameter id="I-128"/>
		<parameter id="O-134"/>
	</service>
	<service id="Service-50">
		<parameter id="I-134"/>
		<parameter id="I-130"/>
		<parameter id="I-133"/>
		<parameter id="I-132"/>
		<parameter id="O-139"/>
		<parameter id="O-140"/>
		<parameter id="O-141"/>
	</service>
	<service id="Service-52">
		<parameter id="I-130"/>
		<parameter id="O-146"/>
		<parameter id="O-147"/>
	</service>
	<service id="Service-55">
		<parameter id="I-148"/>
		<parameter id="O-154"/>
	</service>
	<service id="Service-56">
		<parameter id="I-148"/>
		<parameter id="O-155"/>
		<parameter id="O-156"/>
		<parameter id="O-157"/>
	</service>
	<service id="Service-57">
		<parameter id="I-152"/>
		<parameter id="I-151"/>
		<parameter id="I-150"/>
		<parameter id="O-158"/>
		<parameter id="O-159"/>
		<parameter id="O-160"/>
	</service>
	<service id="Service-64">
		<parameter id="I-173"/>
		<parameter id="I-174"/>
		<parameter id="O-175"/>
		<parameter id="O-176"/>
		<parameter id="O-177"/>
		<parameter id="O-178"/>
	</service>
	<service id="Service-70">
		<parameter id="I-186"/>
		<parameter id="O-189"/>
		<parameter id="O-190"/>
		<parameter id="O-191"/>
	</service>
	<service id="Service-72">
		<parameter id="I-193"/>
		<parameter id="O-196"/>
		<parameter id="O-197"/>
		<parameter id="O-198"/>
		<parameter id="O-199"/>
	</service>
	<service id="Service-73">
		<parameter id="I-192"/>
		<parameter id="O-200"/>
		<parameter id="O-201"/>
		<parameter id="O-202"/>
	</service>
	<service id="Service-75">
		<parameter id="I-199"/>
		<parameter id="I-197"/>
		<parameter id="I-200"/>
		<parameter id="O-206"/>
		<parameter id="O-207"/>
		<parameter id="O-208"/>
		<parameter id="O-209"/>
	</service>
	<service id="Service-76">
		<parameter id="I-204"/>
		<parameter id="I-197"/>
		<parameter id="I-202"/>
		<parameter id="I-201"/>
		<parameter id="O-210"/>
		<parameter id="O-211"/>
		<parameter id="O-212"/>
		<parameter id="O-213"/>
	</service>
	<service id="Service-78">
		<parameter id="I-210"/>
		<parameter id="I-207"/>
		<parameter id="I-209"/>
		<parameter id="O-218"/>
		<parameter id="O-219"/>
		<parameter id="O-220"/>
		<parameter id="O-221"/>
	</service>
	<service id="Service-79">
		<parameter id="I-218"/>
		<parameter id="O-222"/>
		<parameter id="O-223"/>
		<parameter id="O-224"/>
		<parameter id="O-225"/>
	</service>
	<service id="Service-80">
		<parameter id="I-218"/>
		<parameter id="O-226"/>
		<parameter id="O-227"/>
	</service>
	<service id="Service-89">
		<parameter id="I-243"/>
		<parameter id="I-242"/>
		<parameter id="I-241"/>
		<parameter id="O-246"/>
		<parameter id="O-247"/>
		<parameter id="O-248"/>
	</service>
	<service id="Service-96">
		<parameter id="I-265"/>
		<parameter id="I-264"/>
		<parameter id="I-263"/>
		<parameter id="O-269"/>
		<parameter id="O-270"/>
	</service>
</services>
